pyecf/__init__.py
pyecf/ecp/__init__.py
pyecf/ecp/curve.py
pyecf/ecp/point.py
pyecf/lenstras_algo.py
pyecf/scripts/__init__.py
pyecf/scripts/pyecf.py
pyecf/utils/__init__.py
pyecf/utils/gcd.py
pyecf/utils/misc.py
pyecf-0.1.3.dist-info/LICENSE
pyecf-0.1.3.dist-info/METADATA
pyecf-0.1.3.dist-info/WHEEL
pyecf-0.1.3.dist-info/entry_points.txt
pyecf-0.1.3.dist-info/RECORD
