Metadata-Version: 2.1
Name: pyecf
Version: 0.1.3
Summary: Elliptic Curve Factorization
License: MIT
Author: Nikita Yurasov
Author-email: n.yurasov@yahoo.com
Requires-Python: >=3.9,<4.0
Classifier: License :: OSI Approved :: MIT License
Classifier: Programming Language :: Python :: 3
Classifier: Programming Language :: Python :: 3.9
Classifier: Programming Language :: Python :: 3.10
Classifier: Programming Language :: Python :: 3.11
Requires-Dist: gmpy2 (>=2.1,<3.0)
Requires-Dist: matplotlib (>=3.8,<4.0)
Requires-Dist: numpy (>=1.26,<2.0)
Requires-Dist: sympy (>=1.12,<2.0)
Requires-Dist: tqdm (>=4.66,<5.0)
Requires-Dist: typer (>=0.9,<0.10)
